README.rst
python_json2yaml.py
setup.py
python_json2yaml.egg-info/PKG-INFO
python_json2yaml.egg-info/SOURCES.txt
python_json2yaml.egg-info/dependency_links.txt
python_json2yaml.egg-info/entry_points.txt
python_json2yaml.egg-info/requires.txt
python_json2yaml.egg-info/top_level.txt