Metadata-Version: 1.1
Name: python-json2yaml
Version: 0.1.1
Summary: A simple command that turn json data to yaml format and vice versa. It can be used in Linux, MacOS and Window.
Home-page: https://github.com/appstore-zencore/python-json2yaml
Author: zencore
Author-email: dobetter@zencore.cn
License: MIT
Keywords: python-json2yaml,json2yaml,yaml2json
Platform: UNKNOWN
Classifier: Development Status :: 5 - Production/Stable
Classifier: Intended Audience :: Developers
Classifier: Topic :: Software Development :: Libraries :: Python Modules
Classifier: License :: OSI Approved :: MIT License
Classifier: Programming Language :: Python :: 3
Classifier: Programming Language :: Python :: 3 :: Only
Requires: pyyaml
Requires: click
